{
  "main": {
    "id": "f667ce2dc2efe0b1",
    "type": "split",
    "children": [
      {
        "id": "2df938493679793a",
        "type": "tabs",
        "children": [
          {
            "id": "e6e9676f41f779fb",
            "type": "leaf",
            "pane-relief:history-v1": {
              "pos": 0,
              "stack": [
                {
                  "state": "{}",
                  "eState": "{}"
                }
              ]
            },
            "state": {
              "type": "markdown",
              "state": {
                "file": "Advanced HTML & CSS/Cheat Sheets/CSS Properties pt.1.md",
                "mode": "source",
                "source": false
              }
            }
          },
          {
            "id": "4af3067eca517182",
            "type": "leaf",
            "pane-relief:history-v1": {
              "pos": 0,
              "stack": [
                {
                  "state": "{}",
                  "eState": "{}"
                }
              ]
            },
            "state": {
              "type": "markdown",
              "state": {
                "file": "Advanced HTML & CSS/Advanced Selectors.md",
                "mode": "source",
                "source": false
              }
            }
          },
          {
            "id": "7bdf78072fef9ab7",
            "type": "leaf",
            "pane-relief:history-v1": {
              "pos": 0,
              "stack": [
                {
                  "state": "{}",
                  "eState": "{}"
                }
              ]
            },
            "state": {
              "type": "markdown",
              "state": {
                "file": "Advanced HTML & CSS/Cheat Sheets/CSS Selectors Cheat Sheet.md",
                "mode": "source",
                "source": false
              }
            }
          },
          {
            "id": "7cefc388799a5239",
            "type": "leaf",
            "pane-relief:history-v1": {
              "pos": 0,
              "stack": [
                {
                  "state": "{}",
                  "eState": "{}"
                },
                {
                  "title": "cheatsheet-a5",
                  "icon": "lucide-file-text",
                  "state": "{\"type\":\"pdf\",\"state\":{\"file\":\"Storage/cheatsheet-a5.pdf\"}}",
                  "eState": "{}"
                },
                {
                  "title": "wsu-css-cheat-sheet-gdocs",
                  "icon": "lucide-file-text",
                  "state": "{\"type\":\"pdf\",\"state\":{\"file\":\"Storage/wsu-css-cheat-sheet-gdocs.pdf\"}}",
                  "eState": "{}"
                },
                {
                  "title": "Positioning",
                  "icon": "lucide-file",
                  "state": "{\"type\":\"markdown\",\"state\":{\"file\":\"Advanced HTML & CSS/Positioning.md\",\"mode\":\"source\",\"source\":false}}",
                  "eState": "{\"cursor\":{\"from\":{\"line\":25,\"ch\":488},\"to\":{\"line\":25,\"ch\":488}},\"scroll\":18.175786882540155}"
                }
              ]
            },
            "state": {
              "type": "markdown",
              "state": {
                "file": "Advanced HTML & CSS/Терминология.md",
                "mode": "source",
                "source": false
              }
            }
          },
          {
            "id": "feb4d6d8282653c8",
            "type": "leaf",
            "pane-relief:history-v1": {
              "pos": 0,
              "stack": [
                {
                  "state": "{}",
                  "eState": "{}"
                }
              ]
            },
            "state": {
              "type": "markdown",
              "state": {
                "file": "Advanced HTML & CSS/CSS Functions.md",
                "mode": "source",
                "source": false
              }
            }
          }
        ],
        "currentTab": 4
      }
    ],
    "direction": "vertical"
  },
  "left": {
    "id": "3b92f8cbc2af79f1",
    "type": "split",
    "children": [
      {
        "id": "281d71b5990ed718",
        "type": "tabs",
        "children": [
          {
            "id": "83a247297d45001c",
            "type": "leaf",
            "pane-relief:history-v1": {
              "pos": 0,
              "stack": [
                {
                  "state": "{}",
                  "eState": "{}"
                }
              ]
            },
            "state": {
              "type": "search",
              "state": {
                "query": "",
                "matchingCase": true,
                "explainSearch": false,
                "collapseAll": false,
                "extraContext": false,
                "sortOrder": "alphabetical"
              }
            }
          },
          {
            "id": "15da92c398d3a07a",
            "type": "leaf",
            "pane-relief:history-v1": {
              "pos": 0,
              "stack": [
                {
                  "state": "{}",
                  "eState": "{}"
                }
              ]
            },
            "state": {
              "type": "starred",
              "state": {}
            }
          },
          {
            "id": "4356fe038514e5a7",
            "type": "leaf",
            "pane-relief:history-v1": {
              "pos": 0,
              "stack": [
                {
                  "state": "{}",
                  "eState": "{}"
                }
              ]
            },
            "state": {
              "type": "file-explorer",
              "state": {
                "sortOrder": "alphabetical"
              }
            }
          }
        ],
        "currentTab": 2
      }
    ],
    "direction": "horizontal",
    "width": 200
  },
  "right": {
    "id": "e6dcb0954fc4b331",
    "type": "split",
    "children": [
      {
        "id": "92ff108aa2a0d540",
        "type": "tabs",
        "children": [
          {
            "id": "d61375cc2ea354b2",
            "type": "leaf",
            "pane-relief:history-v1": {
              "pos": 0,
              "stack": [
                {
                  "state": "{}",
                  "eState": "{}"
                }
              ]
            },
            "state": {
              "type": "outgoing-link",
              "state": {
                "file": "Advanced HTML & CSS/CSS Functions.md",
                "linksCollapsed": false,
                "unlinkedCollapsed": true
              }
            }
          },
          {
            "id": "3eecd288a135ee98",
            "type": "leaf",
            "pane-relief:history-v1": {
              "pos": 0,
              "stack": [
                {
                  "state": "{}",
                  "eState": "{}"
                }
              ]
            },
            "state": {
              "type": "tag",
              "state": {
                "sortOrder": "frequency",
                "useHierarchy": true
              }
            }
          },
          {
            "id": "7782daa7f50da187",
            "type": "leaf",
            "pane-relief:history-v1": {
              "pos": 0,
              "stack": [
                {
                  "state": "{}",
                  "eState": "{}"
                }
              ]
            },
            "state": {
              "type": "outline",
              "state": {
                "file": "Advanced HTML & CSS/CSS Functions.md"
              }
            }
          },
          {
            "id": "deee0e75fee9485f",
            "type": "leaf",
            "pane-relief:history-v1": {
              "pos": 0,
              "stack": [
                {
                  "state": "{}",
                  "eState": "{}"
                }
              ]
            },
            "state": {
              "type": "BC-matrix",
              "state": {}
            }
          },
          {
            "id": "d933a16f9154763f",
            "type": "leaf",
            "pane-relief:history-v1": {
              "pos": 0,
              "stack": [
                {
                  "state": "{}",
                  "eState": "{}"
                }
              ]
            },
            "state": {
              "type": "BC-tree",
              "state": {}
            }
          },
          {
            "id": "c8bf9dd7b8e26377",
            "type": "leaf",
            "pane-relief:history-v1": {
              "pos": 0,
              "stack": [
                {
                  "state": "{}",
                  "eState": "{}"
                }
              ]
            },
            "state": {
              "type": "advanced-tables-toolbar",
              "state": {}
            }
          },
          {
            "id": "3ddc8e63bd90141b",
            "type": "leaf",
            "pane-relief:history-v1": {
              "pos": 0,
              "stack": [
                {
                  "state": "{}",
                  "eState": "{}"
                }
              ]
            },
            "state": {
              "type": "backlink",
              "state": {
                "file": "Advanced HTML & CSS/CSS Functions.md",
                "collapseAll": false,
                "extraContext": false,
                "sortOrder": "alphabetical",
                "showSearch": false,
                "searchQuery": "",
                "backlinkCollapsed": false,
                "unlinkedCollapsed": true
              }
            }
          }
        ]
      }
    ],
    "direction": "horizontal",
    "width": 300,
    "collapsed": true
  },
  "left-ribbon": {
    "hiddenItems": {
      "switcher:Open quick switcher": false,
      "graph:Open graph view": false,
      "canvas:Create new canvas": false,
      "daily-notes:Open today's daily note": false,
      "templates:Insert template": false,
      "command-palette:Open command palette": false,
      "templater-obsidian:Templater": false,
      "obsidian-excalidraw-plugin:Create new drawing": false,
      "table-editor-obsidian:Advanced Tables Toolbar": false,
      "breadcrumbs:Breadcrumbs Visualisation": false
    }
  },
  "active": "4356fe038514e5a7",
  "lastOpenFiles": [
    "Advanced HTML & CSS/Терминология.md",
    "Storage/cheatsheet-a5.pdf",
    "Storage/wsu-css-cheat-sheet-gdocs.pdf",
    "Pasted image 20230218155443.jpg",
    "Advanced HTML & CSS/Positioning.md",
    "Advanced HTML & CSS/Cheat Sheets.md",
    "Advanced HTML & CSS/Cheat Sheets/CSS Selectors Cheat Sheet.md",
    "Advanced HTML & CSS/Advanced Selectors.md",
    "Advanced HTML & CSS/Cheat Sheets/CSS Properties pt.1.md",
    "Advanced HTML & CSS/Tips And Tricks/Truncate String with Ellipsis.md"
  ]
}